{
  "url": "https://www.telekom.de/optionsuebersicht/festnetz/webhosting",
  "brand": "Telekom",
  "product_ids": [
    "dsl"
  ],
  "text": "...\nTelekom\n...\n...\nWartungsseite\n...\n...\nAktuell aktualisieren wir unsere Angebote für Sie\n...\nBitte haben Sie einen Moment Geduld.\nAktuell ist die Nachfrage besonders hoch, daher kommt es vorübergehend zu Einschränkungen.\nWir arbeiten mit Hochdruck an einer Lösung.\nVielen Dank für Ihr Verständnis.\nRufen Sie uns an\nBestellung:\n0800 33 03000\nWM 2026 Bestellung:\n0800 33 06775\nKundenservice Festnetz:\n0800 33 01000\nKundenservice Mobilfunk:\n0800 33 02202",
  "text_hash": "5df2eaea774b802d",
  "status": 200,
  "timestamp": "2026-07-13T18-35-25Z"
}
